README.md
setup.py
pyRoIS.egg-info/PKG-INFO
pyRoIS.egg-info/SOURCES.txt
pyRoIS.egg-info/dependency_links.txt
pyRoIS.egg-info/top_level.txt
pyrois/HRI_Engine_client.py
pyrois/HRI_Engine_sample.py
pyrois/IF_server.py
pyrois/Person_Detection.py
pyrois/Person_Detection_client.py
pyrois/RoIS_Common.py
pyrois/RoIS_HRI.py
pyrois/RoIS_Service.py
pyrois/Service_Application_Base_sample.py
pyrois/Service_Application_IF.py
pyrois/__init__.py